caqtus_devices/arbitrary_waveform_generators/ni_6738/__init__.py
caqtus_devices/arbitrary_waveform_generators/ni_6738/_compiler.py
caqtus_devices/arbitrary_waveform_generators/ni_6738/_extension.py
caqtus_devices/arbitrary_waveform_generators/ni_6738/py.typed
caqtus_devices/arbitrary_waveform_generators/ni_6738/configuration/__init__.py
caqtus_devices/arbitrary_waveform_generators/ni_6738/configuration/configuration.py
caqtus_devices/arbitrary_waveform_generators/ni_6738/configuration_editor/__init__.py
caqtus_devices/arbitrary_waveform_generators/ni_6738/configuration_editor/editor.py
caqtus_devices/arbitrary_waveform_generators/ni_6738/runtime/__init__.py
caqtus_devices/arbitrary_waveform_generators/ni_6738/runtime/runtime.py
caqtus_devices_ni_6738-1.13.0.dist-info/METADATA
caqtus_devices_ni_6738-1.13.0.dist-info/WHEEL
caqtus_devices_ni_6738-1.13.0.dist-info/licenses/license.md
caqtus_devices_ni_6738-1.13.0.dist-info/RECORD
