Metadata-Version: 2.4
Name: caqtus-devices-ni-6738
Version: 1.13.0
Summary: Contains the caqtus device extension for the NI6738 analog output card.
Author-email: light-scattering-io <lecaqtus66@gmail.com>
License: Copyright 2024 Université Paris-Saclay
License-File: license.md
Requires-Python: >=3.12
Requires-Dist: caqtus-suite>=6.18.1
Requires-Dist: nidaqmx>=1.0.2
Requires-Dist: pyside6!=6.8.1.1,>=6.8.1
